{"total_count": 6, "items": [{"etag": "8728f052fca68a97c9dc3bc42e95858890aa6ec5", "classification": {"type": "charge-description", "description": "Legal mortgage"}, "charge_number": 6, "status": "fully-satisfied", "delivered_on": "1996-02-28", "created_on": "1996-02-23", "satisfied_on": "2020-11-03", "particulars": {"type": "short-particulars", "description": "F/H land on the north east side of horse hill, horley surrey t/n SY578101 and f/h land and buildings on the north east side of horsehills road and on the south west side of crutchfield lane charlwood t/n SY134699."}, "secured_details": {"type": "amount-secured", "description": "\u00a3142,937.50 due or to become due from the company to the chargee"}, "persons_entitled": [{"name": "Cowbridge Investments Limited"}], "transactions": [{"filing_type": "create-charge-pre-2006-companies-act", "delivered_on": "1996-02-28", "links": {"filing": "/company/01784809/filing-history/MDAxOTAyMDYyN2FkaXF6a2N4"}}, {"filing_type": "charge-satisfaction", "delivered_on": "2020-11-03", "links": {"filing": "/company/01784809/filing-history/MzI4MjM3MTA0NGFkaXF6a2N4"}}], "links": {"self": "/company/01784809/charges/b7xxmDBwaeZqfF1WV8hzb_BvXdg"}}, {"etag": "fc39b908783f3955736a2518341372f911003ee5", "classification": {"type": "charge-description", "description": "Legal charge"}, "charge_number": 5, "status": "fully-satisfied", "delivered_on": "1995-01-28", "created_on": "1995-01-19", "satisfied_on": "1998-11-10", "particulars": {"type": "short-particulars", "description": "All that f/h land at the north east side of horse hill road and south west side of crutchfield lane charlwood surrey title number SY134699."}, "secured_details": {"type": "amount-secured", "description": "\u00a360,000.00 due from the company to the chargee under the terms of the said agreement"}, "persons_entitled": [{"name": "Domitia Limited"}], "transactions": [{"filing_type": "create-charge-pre-2006-companies-act", "delivered_on": "1995-01-28", "links": {"filing": "/company/01784809/filing-history/MDAzMzEyNjk4OGFkaXF6a2N4"}}, {"filing_type": "charge-satisfaction-pre-2006-companies-act", "delivered_on": "1998-11-10", "links": {"filing": "/company/01784809/filing-history/MDA2NDk3MzU0NmFkaXF6a2N4"}}], "links": {"self": "/company/01784809/charges/S7LRqXywDdu8eaoXmt24QvIlXds"}}, {"etag": "5a78dbcf5a12003a1888a2ca585c8c8cfa48bdfa", "classification": {"type": "charge-description", "description": "Legal charge"}, "charge_number": 4, "status": "fully-satisfied", "delivered_on": "1988-08-05", "created_on": "1988-07-28", "satisfied_on": "1995-02-02", "particulars": {"type": "short-particulars", "description": "Stable block adjoining high trees school, horley, surrey t/ n sy 541105."}, "secured_details": {"type": "amount-secured", "description": "All monies due or to become due from the company to the chargee on any account whatsoever"}, "persons_entitled": [{"name": "Barclays Bank PLC"}], "transactions": [{"filing_type": "create-charge", "delivered_on": "1988-08-05"}, {"filing_type": "charge-satisfaction-pre-2006-companies-act", "delivered_on": "1995-02-02", "links": {"filing": "/company/01784809/filing-history/YWRpcXprY3g"}}], "links": {"self": "/company/01784809/charges/kG0bUR9Wn0btSX8uZZL1wHxmS4M"}}, {"etag": "e7981668b32ce5e7a15d636da73c10fd413ebf5f", "classification": {"type": "charge-description", "description": "Legal charge"}, "charge_number": 3, "status": "fully-satisfied", "delivered_on": "1985-02-21", "created_on": "1985-02-14", "satisfied_on": "2020-11-03", "particulars": {"type": "short-particulars", "description": "High trees school, horley, surrey."}, "secured_details": {"type": "amount-secured", "description": "All monies due or to become due from the company to the chargee on any account whatsoever"}, "persons_entitled": [{"name": "Barclays Bank PLC"}], "transactions": [{"filing_type": "create-charge", "delivered_on": "1985-02-21"}, {"filing_type": "charge-satisfaction", "delivered_on": "2020-11-03", "links": {"filing": "/company/01784809/filing-history/MzI4MjM3MDQ5MmFkaXF6a2N4"}}], "links": {"self": "/company/01784809/charges/3wmPSVFB409NlQzMvCX227VHhO8"}}, {"etag": "76e7e8a6db285f0570b9394a53e592fd3edf9c61", "classification": {"type": "charge-description", "description": "Legal charge"}, "charge_number": 2, "status": "fully-satisfied", "delivered_on": "1985-02-21", "created_on": "1985-02-14", "satisfied_on": "2020-11-03", "particulars": {"type": "short-particulars", "description": "Land adjoining high trees school, horley, surrey."}, "secured_details": {"type": "amount-secured", "description": "All monies due or to become due from the company to the chargee on any account whatsoever"}, "persons_entitled": [{"name": "Barclays Bank PLC"}], "transactions": [{"filing_type": "create-charge", "delivered_on": "1985-02-21"}, {"filing_type": "charge-satisfaction", "delivered_on": "2020-11-03", "links": {"filing": "/company/01784809/filing-history/MzI4MjM3MDQ5NWFkaXF6a2N4"}}], "links": {"self": "/company/01784809/charges/K83L-Em4a9lLyyy6SjGUjVy1GE8"}}, {"etag": "621b5d035599fb6596858639f59060ffe7fdfc8c", "classification": {"type": "charge-description", "description": "Legal charge"}, "charge_number": 1, "status": "fully-satisfied", "delivered_on": "1985-02-21", "created_on": "1985-02-14", "satisfied_on": "1995-02-02", "particulars": {"type": "short-particulars", "description": "Stable block adjoining high trees school, horley, surrey."}, "secured_details": {"type": "amount-secured", "description": "All monies due or to become due from the company to the chargee on any account whatsoever"}, "persons_entitled": [{"name": "Barclays Bank PLC"}], "transactions": [{"filing_type": "create-charge", "delivered_on": "1985-02-21"}, {"filing_type": "charge-satisfaction-pre-2006-companies-act", "delivered_on": "1995-02-02", "links": {"filing": "/company/01784809/filing-history/YWRpcXprY3g"}}], "links": {"self": "/company/01784809/charges/xyWv84bCrn-oAqZPVeiPm_KS79A"}}]}