{"total_count": 18, "items": [{"etag": "07d2c35141577b529c5aae44ad929f9c5bb9a3c7", "charge_code": "047355720020", "classification": {"type": "charge-description", "description": "A registered charge"}, "charge_number": 20, "status": "outstanding", "delivered_on": "2025-07-08", "created_on": "2025-07-04", "particulars": {"type": "brief-description", "description": "820 green lanes, london, N21 2RT (title number MX234165).", "contains_fixed_charge": true, "contains_negative_pledge": true}, "persons_entitled": [{"name": "Lhv Bank Limited"}], "transactions": [{"filing_type": "create-charge-with-deed", "delivered_on": "2025-07-08", "links": {"filing": "/company/04735572/filing-history/MzQ3Mjg3MzExMGFkaXF6a2N4"}}], "links": {"self": "/company/04735572/charges/AoOIBVcv44-9Q3AZoEdBDZdh0cc"}}, {"etag": "c42321aa2633401b1a6205a5663bcc135a2c47a1", "charge_code": "047355720019", "classification": {"type": "charge-description", "description": "A registered charge"}, "charge_number": 19, "status": "outstanding", "delivered_on": "2022-08-03", "created_on": "2022-08-02", "particulars": {"type": "brief-description", "description": "The freehold property known as 20 leighton road, bush hill park, EN1 1XJ under title number AGL123071.", "contains_floating_charge": true, "contains_fixed_charge": true, "floating_charge_covers_all": true, "contains_negative_pledge": true}, "persons_entitled": [{"name": "Monument Bank Limited"}], "transactions": [{"filing_type": "create-charge-with-deed", "delivered_on": "2022-08-03", "links": {"filing": "/company/04735572/filing-history/MzM0NzY4MzEyNGFkaXF6a2N4"}}], "links": {"self": "/company/04735572/charges/CqilFeBAN9Sp5L3_xRHXwgB3ibU"}}, {"etag": "8ee33bf4ce3e053c3f1b45cd28f6f65cba7cb22f", "charge_code": "047355720018", "classification": {"type": "charge-description", "description": "A registered charge"}, "charge_number": 18, "status": "outstanding", "delivered_on": "2022-07-18", "created_on": "2022-07-15", "particulars": {"type": "brief-description", "description": "The freehold property known as 35 langham road, tottenham, N15 3QX under title number MX255629. The freehold property known as 37 langham road, tottenham, N15 3QX under title number MX444683. The freehold property known as 39 langham road, tottenham, N15 3QX under title number MX239499. For further details of property charged please see the deed.", "contains_floating_charge": true, "contains_fixed_charge": true, "floating_charge_covers_all": true, "contains_negative_pledge": true}, "persons_entitled": [{"name": "Monument Bank Limited"}], "transactions": [{"filing_type": "create-charge-with-deed", "delivered_on": "2022-07-18", "links": {"filing": "/company/04735572/filing-history/MzM0NTk3MzE0MmFkaXF6a2N4"}}], "links": {"self": "/company/04735572/charges/tUMqhulDoIznNvfE4zfCrAYNTJU"}}, {"etag": "6cfa7860d653762b93c2153234285d6c68add9d4", "charge_code": "047355720017", "classification": {"type": "charge-description", "description": "A registered charge"}, "charge_number": 17, "status": "outstanding", "delivered_on": "2022-06-01", "created_on": "2022-05-31", "particulars": {"type": "brief-description", "description": "The freehold property known as 61 bury street, N9 7JN with title no EGL175042.", "contains_floating_charge": true, "contains_fixed_charge": true, "floating_charge_covers_all": true, "contains_negative_pledge": true}, "persons_entitled": [{"name": "Monument Bank Limited"}], "transactions": [{"filing_type": "create-charge-with-deed", "delivered_on": "2022-06-01", "links": {"filing": "/company/04735572/filing-history/MzM0MTI2NjkzNWFkaXF6a2N4"}}], "links": {"self": "/company/04735572/charges/4mWZiJufM1rmbRFGagKnHwFz5Uw"}}, {"etag": "396d687cd3c27a371a9f67e25d056ef81d22846d", "charge_code": "047355720016", "classification": {"type": "charge-description", "description": "A registered charge"}, "charge_number": 16, "status": "outstanding", "delivered_on": "2022-04-04", "created_on": "2022-04-01", "particulars": {"type": "brief-description", "description": "The freehold property known as 29 westfield close, EN3 7RU.", "contains_floating_charge": true, "contains_fixed_charge": true, "floating_charge_covers_all": true, "contains_negative_pledge": true}, "persons_entitled": [{"name": "Monument Bank Limited"}], "transactions": [{"filing_type": "create-charge-with-deed", "delivered_on": "2022-04-04", "links": {"filing": "/company/04735572/filing-history/MzMzNTE2MjMyN2FkaXF6a2N4"}}], "links": {"self": "/company/04735572/charges/S9dTNcdNZh2B9g6GeNjALG2IZSk"}}, {"etag": "29df7f7829d37a4504864325cf1e6dc8a77fc1d3", "charge_code": "047355720015", "classification": {"type": "charge-description", "description": "A registered charge"}, "charge_number": 15, "status": "fully-satisfied", "delivered_on": "2018-07-03", "created_on": "2018-06-28", "satisfied_on": "2022-10-17", "particulars": {"type": "brief-description", "description": "84 warwick road, london N18 1RT.", "contains_floating_charge": true, "contains_fixed_charge": true, "floating_charge_covers_all": true, "contains_negative_pledge": true}, "persons_entitled": [{"name": "Metro Bank PLC"}], "transactions": [{"filing_type": "create-charge-with-deed", "delivered_on": "2018-07-03", "links": {"filing": "/company/04735572/filing-history/MzIwODkwMDgwNWFkaXF6a2N4"}}, {"filing_type": "charge-satisfaction", "delivered_on": "2022-10-17", "links": {"filing": "/company/04735572/filing-history/MzM1NTUwNDA1NGFkaXF6a2N4"}}], "links": {"self": "/company/04735572/charges/yEbMonvAjCL9pfX39PWp-gXRwso"}}, {"etag": "0e277b1ac194db82875b4ff18864b4724126bb26", "charge_code": "047355720014", "classification": {"type": "charge-description", "description": "A registered charge"}, "charge_number": 14, "status": "fully-satisfied", "delivered_on": "2018-06-29", "created_on": "2018-06-28", "satisfied_on": "2022-10-17", "particulars": {"type": "brief-description", "description": "38 forest road, london N9 8RX.", "contains_floating_charge": true, "contains_fixed_charge": true, "floating_charge_covers_all": true, "contains_negative_pledge": true}, "persons_entitled": [{"name": "Metro Bank PLC"}], "transactions": [{"filing_type": "create-charge-with-deed", "delivered_on": "2018-06-29", "links": {"filing": "/company/04735572/filing-history/MzIwODY4NjI0NGFkaXF6a2N4"}}, {"filing_type": "charge-satisfaction", "delivered_on": "2022-10-17", "links": {"filing": "/company/04735572/filing-history/MzM1NTUwMzgyNmFkaXF6a2N4"}}], "links": {"self": "/company/04735572/charges/JUEhBXt-CyLVaOuQepdscUDE2nM"}}, {"etag": "ce2781e838ebb82efe8824add0293eba7906c0d8", "charge_code": "047355720013", "classification": {"type": "charge-description", "description": "A registered charge"}, "charge_number": 13, "status": "fully-satisfied", "delivered_on": "2018-06-29", "created_on": "2018-06-28", "satisfied_on": "2022-10-17", "particulars": {"type": "brief-description", "description": "9 hewish road, london N18 1PS.", "contains_floating_charge": true, "contains_fixed_charge": true, "floating_charge_covers_all": true, "contains_negative_pledge": true}, "persons_entitled": [{"name": "Metro Bank PLC"}], "transactions": [{"filing_type": "create-charge-with-deed", "delivered_on": "2018-06-29", "links": {"filing": "/company/04735572/filing-history/MzIwODY4NTg3NmFkaXF6a2N4"}}, {"filing_type": "charge-satisfaction", "delivered_on": "2022-10-17", "links": {"filing": "/company/04735572/filing-history/MzM1NTUwMzMwOWFkaXF6a2N4"}}], "links": {"self": "/company/04735572/charges/RNBR4Ov6DWgFShAvgWtMSB-b2xk"}}, {"etag": "52d49265252be8e425cb3a69e9c3fd0ce66a862b", "charge_code": "047355720012", "classification": {"type": "charge-description", "description": "A registered charge"}, "charge_number": 12, "status": "fully-satisfied", "delivered_on": "2018-06-29", "created_on": "2018-06-28", "satisfied_on": "2022-10-17", "particulars": {"type": "brief-description", "description": "77 hudson way, london N9 0XE.", "contains_floating_charge": true, "contains_fixed_charge": true, "floating_charge_covers_all": true, "contains_negative_pledge": true}, "persons_entitled": [{"name": "Metro Bank PLC"}], "transactions": [{"filing_type": "create-charge-with-deed", "delivered_on": "2018-06-29", "links": {"filing": "/company/04735572/filing-history/MzIwODY4NTMyOWFkaXF6a2N4"}}, {"filing_type": "charge-satisfaction", "delivered_on": "2022-10-17", "links": {"filing": "/company/04735572/filing-history/MzM1NTUwMzEwNWFkaXF6a2N4"}}], "links": {"self": "/company/04735572/charges/FghZUNcwr9da_-fN_E9gbpKPT5U"}}, {"etag": "93dea3ccfe2ad668bbc5315b744f037f75382941", "charge_code": "047355720011", "classification": {"type": "charge-description", "description": "A registered charge"}, "charge_number": 11, "status": "fully-satisfied", "delivered_on": "2018-06-29", "created_on": "2018-06-28", "satisfied_on": "2022-10-17", "particulars": {"type": "brief-description", "description": "10 harton road, london N9 0SG.", "contains_floating_charge": true, "contains_fixed_charge": true, "floating_charge_covers_all": true, "contains_negative_pledge": true}, "persons_entitled": [{"name": "Metro Bank PLC"}], "transactions": [{"filing_type": "create-charge-with-deed", "delivered_on": "2018-06-29", "links": {"filing": "/company/04735572/filing-history/MzIwODY4NDgyM2FkaXF6a2N4"}}, {"filing_type": "charge-satisfaction", "delivered_on": "2022-10-17", "links": {"filing": "/company/04735572/filing-history/MzM1NTUwMjM4NGFkaXF6a2N4"}}], "links": {"self": "/company/04735572/charges/yHxf_PAppHnqQGi1wU84MAV7AB4"}}, {"etag": "7e48b4c7220a504b89ffbd26c0ad6f550b314ac9", "charge_code": "047355720010", "classification": {"type": "charge-description", "description": "A registered charge"}, "charge_number": 10, "status": "fully-satisfied", "delivered_on": "2017-02-11", "created_on": "2016-03-29", "satisfied_on": "2022-10-17", "particulars": {"type": "brief-description", "description": "F/H property k/a 6 meads road enfield t/no EGL220166.", "contains_floating_charge": true, "contains_fixed_charge": true, "contains_negative_pledge": true}, "persons_entitled": [{"name": "Metro Bank PLC"}], "transactions": [{"filing_type": "create-charge-with-deed-with-court-order", "delivered_on": "2017-02-11", "links": {"filing": "/company/04735572/filing-history/MzE3MDY2MzgxMmFkaXF6a2N4"}}, {"filing_type": "charge-satisfaction", "delivered_on": "2022-10-17", "links": {"filing": "/company/04735572/filing-history/MzM1NTUwMjI3MGFkaXF6a2N4"}}], "links": {"self": "/company/04735572/charges/HkAuhIL3Vd0uCZlO4do1HPhtlXA"}}, {"etag": "e88785f40bab1a858bb76caf1f0f0e3281ed9337", "charge_code": "047355720009", "classification": {"type": "charge-description", "description": "A registered charge"}, "charge_number": 9, "status": "fully-satisfied", "delivered_on": "2017-02-11", "created_on": "2016-03-29", "satisfied_on": "2022-10-17", "particulars": {"type": "brief-description", "description": "F/H property k/a 22 ashford crescent enfield t/no AGL151438.", "contains_floating_charge": true, "contains_fixed_charge": true, "contains_negative_pledge": true}, "persons_entitled": [{"name": "Metro Bank PLC"}], "transactions": [{"filing_type": "create-charge-with-deed-with-court-order", "delivered_on": "2017-02-11", "links": {"filing": "/company/04735572/filing-history/MzE3MDY2MzI0OGFkaXF6a2N4"}}, {"filing_type": "charge-satisfaction", "delivered_on": "2022-10-17", "links": {"filing": "/company/04735572/filing-history/MzM1NTUwMTcwNGFkaXF6a2N4"}}], "links": {"self": "/company/04735572/charges/VYIT3DpR8WYJ6xhEJCgrsHpwgD8"}}, {"etag": "5d4500e4a152938a812cfe56c0d0405b58ac3795", "charge_code": "047355720008", "classification": {"type": "charge-description", "description": "A registered charge"}, "charge_number": 8, "status": "fully-satisfied", "delivered_on": "2016-04-12", "created_on": "2016-03-29", "satisfied_on": "2022-10-17", "particulars": {"type": "brief-description", "description": "The freehold property known as 122 kingsway, enfield, EN3 4HU. Title number: NGL203719.", "contains_floating_charge": true, "contains_fixed_charge": true, "floating_charge_covers_all": true, "contains_negative_pledge": true}, "persons_entitled": [{"name": "Metro Bank PLC"}], "transactions": [{"filing_type": "create-charge-with-deed", "delivered_on": "2016-04-12", "links": {"filing": "/company/04735572/filing-history/MzE0NjE1NDQ1M2FkaXF6a2N4"}}, {"filing_type": "charge-satisfaction", "delivered_on": "2022-10-17", "links": {"filing": "/company/04735572/filing-history/MzM1NTUwMTI5MWFkaXF6a2N4"}}], "links": {"self": "/company/04735572/charges/UUPW8OsgMjNqf2mQaIla3BSDewg"}}, {"etag": "34bac7f7ddd2e5e237e972d496b89d44d8f1584b", "classification": {"type": "charge-description", "description": "Legal charge"}, "charge_number": 5, "status": "fully-satisfied", "delivered_on": "2012-07-31", "created_on": "2012-07-16", "satisfied_on": "2022-10-17", "particulars": {"type": "short-particulars", "description": "F/H 35 langham road london t/no MX255629, f/h 37 langham road london t/no MX444683, f/h 39 langham road london t/no MX239499 for details of further property charged please refer to form MG01 fixed charge all present and future estates interest rights and benefits under the terms of any leases in respect of the properties floating charge all unattached plant machinery chattels and goods see image for full details."}, "secured_details": {"type": "amount-secured", "description": "All monies due or to become due from the company to the chargee on any account whatsoever"}, "persons_entitled": [{"name": "Metro Bank PLC"}], "transactions": [{"filing_type": "create-charge-pre-april-2013", "delivered_on": "2012-07-31", "links": {"filing": "/company/04735572/filing-history/MzA2MTg1MjgwNGFkaXF6a2N4"}}, {"filing_type": "charge-satisfaction", "delivered_on": "2022-10-17", "links": {"filing": "/company/04735572/filing-history/MzM1NTUwMDk0M2FkaXF6a2N4"}}], "links": {"self": "/company/04735572/charges/CcbXMUPyXhjVcp3SwMdkNHBGsfo"}}, {"etag": "b9515b9c8985ad5fbc73a544fa9c70a9056795d0", "classification": {"type": "charge-description", "description": "Debenture"}, "charge_number": 4, "status": "fully-satisfied", "delivered_on": "2012-07-31", "created_on": "2012-07-16", "satisfied_on": "2022-08-15", "particulars": {"type": "short-particulars", "description": "By way of fixed and floating charge all its undertaking property and assets whatsoever and wheresoever both present and future."}, "secured_details": {"type": "amount-secured", "description": "All monies due or to become due from the company to the chargee on any account whatsoever under the terms of the aforementioned instrument creating or evidencing the charge"}, "persons_entitled": [{"name": "Metro Bank PLC"}], "transactions": [{"filing_type": "create-charge-pre-april-2013", "delivered_on": "2012-07-31", "links": {"filing": "/company/04735572/filing-history/MzA2MTg1MjcxMGFkaXF6a2N4"}}, {"filing_type": "charge-satisfaction", "delivered_on": "2022-08-15", "links": {"filing": "/company/04735572/filing-history/MzM0ODcwMTA0MmFkaXF6a2N4"}}], "links": {"self": "/company/04735572/charges/wowcyndVGiuRHVVxDHFP3K81Nb8"}}, {"etag": "e6b1965ee0c0aacfd4c78919fba12caee43debaa", "classification": {"type": "charge-description", "description": "Deed of assignment of life policy"}, "charge_number": 3, "status": "fully-satisfied", "delivered_on": "2004-07-30", "created_on": "2004-07-23", "satisfied_on": "2012-08-25", "particulars": {"type": "short-particulars", "description": "A policy held by the company with friends provident life assurance LTD in respect of the life of armando saliba and having policy number 13469586."}, "secured_details": {"type": "amount-secured", "description": "All monies due or to become due from the company to the chargee on any account whatsoever"}, "persons_entitled": [{"name": "National Westminster Bank PLC"}], "transactions": [{"filing_type": "create-charge-pre-2006-companies-act", "delivered_on": "2004-07-30", "links": {"filing": "/company/04735572/filing-history/MDE0MTg4MDA0M2FkaXF6a2N4"}}, {"filing_type": "charge-satisfaction-pre-april-2013", "delivered_on": "2012-08-25", "links": {"filing": "/company/04735572/filing-history/MzA2MzQ0MzM2OWFkaXF6a2N4"}}], "links": {"self": "/company/04735572/charges/tbJTVj1mW36_TiDO8NFhCLFS8SI"}}, {"etag": "c4c3cfce8925904861077dff9419089caa4d2817", "classification": {"type": "charge-description", "description": "Assignment of life policy by way of charge"}, "charge_number": 2, "status": "fully-satisfied", "delivered_on": "2004-06-17", "created_on": "2004-06-07", "satisfied_on": "2012-08-25", "particulars": {"type": "short-particulars", "description": "Policy no 13469586 during the life of armando saliba and all money that may become payable under that policy subject to reassignment on redemption."}, "secured_details": {"type": "amount-secured", "description": "All monies due or to become due from the company to the chargee on any account whatsoever"}, "persons_entitled": [{"name": "National Westminster Bank PLC"}], "transactions": [{"filing_type": "create-charge-pre-2006-companies-act", "delivered_on": "2004-06-17"}, {"filing_type": "charge-satisfaction-pre-april-2013", "delivered_on": "2012-08-25", "links": {"filing": "/company/04735572/filing-history/MzA2MzQ0MzQzNGFkaXF6a2N4"}}], "links": {"self": "/company/04735572/charges/CjcwSGg3UK9byJo2NQnmJZOAz8o"}}, {"etag": "51a32c130958f234768f19469bc0c5f838c0aeb8", "classification": {"type": "charge-description", "description": "Debenture"}, "charge_number": 1, "status": "fully-satisfied", "delivered_on": "2004-06-17", "created_on": "2004-06-07", "satisfied_on": "2012-08-25", "particulars": {"type": "short-particulars", "description": "Fixed and floating charges over the undertaking and all property and assets present and future including goodwill bookdebts uncalled capital buildings fixtures fixed plant and machinery. See the mortgage charge document for full details."}, "secured_details": {"type": "amount-secured", "description": "All monies due or to become due from the company to the chargee on any account whatsoever"}, "persons_entitled": [{"name": "National Westminster Bank PLC"}], "transactions": [{"filing_type": "create-charge-pre-2006-companies-act", "delivered_on": "2004-06-17"}, {"filing_type": "charge-satisfaction-pre-april-2013", "delivered_on": "2012-08-25", "links": {"filing": "/company/04735572/filing-history/MzA2MzQ0MzQ4M2FkaXF6a2N4"}}], "links": {"self": "/company/04735572/charges/rx0raT2HTgZ2Q3P09wR4Clzx4Q0"}}]}