{"total_count": 3, "items": [{"etag": "5d1d13a2052008b576222256c0c359e2bfd44fd5", "classification": {"type": "charge-description", "description": "Legal charge"}, "charge_number": 3, "status": "outstanding", "delivered_on": "2007-06-06", "created_on": "2007-05-22", "particulars": {"type": "short-particulars", "description": "The l/h property known as unit 8 skyways amy johnson way blackpool."}, "secured_details": {"type": "amount-secured", "description": "All monies due or to become due from the company to the chargee on any account whatsoever"}, "persons_entitled": [{"name": "Barclays Bank PLC"}], "transactions": [{"filing_type": "create-charge-pre-2006-companies-act", "delivered_on": "2007-06-06", "links": {"filing": "/company/04881263/filing-history/MDE4MTQxMzcwN2FkaXF6a2N4"}}], "links": {"self": "/company/04881263/charges/xQj4qj9G9NRbKfn1RJUUpYwdzAA"}}, {"etag": "b8ee01c09b3f03ac2089634f98d50a6e2afc3590", "classification": {"type": "charge-description", "description": "Legal charge"}, "charge_number": 2, "status": "outstanding", "delivered_on": "2005-01-28", "created_on": "2005-01-17", "particulars": {"type": "short-particulars", "description": "F/H property k/a clayton works, clayton le moors, accrington, lancashire."}, "secured_details": {"type": "amount-secured", "description": "All monies due or to become due from the company to the chargee on any account whatsoever"}, "persons_entitled": [{"name": "Barclays Bank PLC"}], "transactions": [{"filing_type": "create-charge-pre-2006-companies-act", "delivered_on": "2005-01-28", "links": {"filing": "/company/04881263/filing-history/MDAxMjQ4NjQwN2FkaXF6a2N4"}}], "links": {"self": "/company/04881263/charges/0LQjHdDyA1T4K8Qn-f9NrRuxSxE"}}, {"etag": "1567cb5463d11ebd8e0beb8512f7449221a84430", "classification": {"type": "charge-description", "description": "Debenture"}, "charge_number": 1, "status": "outstanding", "delivered_on": "2005-01-18", "created_on": "2005-01-12", "particulars": {"type": "short-particulars", "description": "By way of fixed charge all land and all other land, all plant and machinery, all rental and other income and all debts, all securities, all insurance and assurance contracts and policies, all goodwill and uncalled capital, all intellectual property, all trade debts and all other debts and the benefit of all insurances guarantees charges pledges and other rights. By way of floating charge all assets not effectively charged."}, "secured_details": {"type": "amount-secured", "description": "All monies due or to become due from the company to the chargee on any account whatsoever"}, "persons_entitled": [{"name": "Barclays Bank PLC"}], "transactions": [{"filing_type": "create-charge-pre-2006-companies-act", "delivered_on": "2005-01-18", "links": {"filing": "/company/04881263/filing-history/MDA4MjUyNDI2NWFkaXF6a2N4"}}], "links": {"self": "/company/04881263/charges/TbGZRpJvRmcbfMPWw8KvNo8lXsc"}}]}