{"total_count": 4, "items": [{"etag": "85b366214ed8eaf999f676c6143dc5211d9232d8", "charge_code": "061946590004", "classification": {"type": "charge-description", "description": "A registered charge"}, "charge_number": 4, "status": "outstanding", "delivered_on": "2026-04-09", "created_on": "2026-03-25", "particulars": {"type": "brief-description", "description": "The studio and four garages, 2 the drive, horley, surrey, RH6 7NG. SY706504.", "contains_fixed_charge": true, "contains_negative_pledge": true}, "persons_entitled": [{"name": "Onesavings Bank PLC"}], "transactions": [{"filing_type": "create-charge-with-deed", "delivered_on": "2026-04-09", "links": {"filing": "/company/06194659/filing-history/MzUxNTE5NDkwOWFkaXF6a2N4"}}], "links": {"self": "/company/06194659/charges/MLaOZNdD4b5ROiyfLNfw4yboCBE"}}, {"etag": "b522edfd528bed967e420c2ff4cd09f0d9bdfeed", "charge_code": "061946590003", "classification": {"type": "charge-description", "description": "A registered charge"}, "charge_number": 3, "status": "outstanding", "delivered_on": "2025-11-13", "created_on": "2025-10-31", "particulars": {"type": "brief-description", "description": "The studio and four garages, 2 the drive, horley, RH6 7NG registered at the land registry with title number SY706504.", "contains_floating_charge": true, "contains_fixed_charge": true, "floating_charge_covers_all": true, "contains_negative_pledge": true}, "persons_entitled": [{"name": "Allica Bridging Finance Limited"}], "transactions": [{"filing_type": "create-charge-with-deed", "delivered_on": "2025-11-13", "links": {"filing": "/company/06194659/filing-history/MzQ4ODY2NTU4MmFkaXF6a2N4"}}], "links": {"self": "/company/06194659/charges/tYb__nw3LKDxme0DsYq5DMQ6h5I"}}, {"etag": "09fd853e74ad2ca28f6077f55781e03162ca5a5a", "charge_code": "061946590002", "classification": {"type": "charge-description", "description": "A registered charge"}, "charge_number": 2, "status": "outstanding", "delivered_on": "2025-11-13", "created_on": "2025-10-31", "particulars": {"type": "brief-description", "description": "The studio and four garages, 2 the drive, horley, RH6 7NG registered at the land registry with title number SY706504.", "contains_fixed_charge": true, "contains_negative_pledge": true}, "persons_entitled": [{"name": "Allica Bridging Finance Limited"}], "transactions": [{"filing_type": "create-charge-with-deed", "delivered_on": "2025-11-13", "links": {"filing": "/company/06194659/filing-history/MzQ4ODY2NTIyNGFkaXF6a2N4"}}], "links": {"self": "/company/06194659/charges/rOvDnE6tT2LfbeVwuOKw-IA08Ho"}}, {"etag": "0469b7cdc03adaa1bf607317ededcd9d13e06991", "classification": {"type": "charge-description", "description": "Legal charge"}, "charge_number": 1, "status": "fully-satisfied", "delivered_on": "2008-12-31", "created_on": "2008-12-18", "satisfied_on": "2025-11-05", "particulars": {"type": "short-particulars", "description": "The studio and 4 garages at 2 the drive horley t/no SY706504 by way of fixed charge, the benefit of all covenants & rights concerning the property & all plant machinery, fixtures, fittings, furniture, equipment, implements & utensils. The goodwill of any business carried on at the property & the proceeds of any insurance affecting the property or assets."}, "secured_details": {"type": "amount-secured", "description": "All monies due or to become due from the company to the chargee on any account whatsoever"}, "persons_entitled": [{"name": "National Westminster Bank PLC"}], "transactions": [{"filing_type": "create-charge-pre-2006-companies-act", "delivered_on": "2008-12-31", "links": {"filing": "/company/06194659/filing-history/MjAyMjE2OTg3MmFkaXF6a2N4"}}, {"filing_type": "charge-satisfaction", "delivered_on": "2025-11-05", "links": {"filing": "/company/06194659/filing-history/MzQ4NzY5NDgzMGFkaXF6a2N4"}}], "links": {"self": "/company/06194659/charges/hSVdYkFruOb2eCWSUF7ft0EUHY4"}}]}