{"total_count": 1, "items": [{"etag": "23c434988696e06758bc3263133767b1dd3cd91a", "charge_code": "084079290001", "classification": {"type": "charge-description", "description": "A registered charge"}, "charge_number": 1, "status": "outstanding", "delivered_on": "2025-07-02", "created_on": "2025-07-02", "particulars": {"contains_floating_charge": true, "contains_fixed_charge": true, "floating_charge_covers_all": true, "contains_negative_pledge": true}, "persons_entitled": [{"name": "Bibby Financial Services LTD"}], "transactions": [{"filing_type": "create-charge-with-deed", "delivered_on": "2025-07-02", "links": {"filing": "/company/08407929/filing-history/MzQ3MjM0Njk3MGFkaXF6a2N4"}}], "links": {"self": "/company/08407929/charges/PH-Eqebh9tbn80bHk3EfReeLC0M"}}]}