{"total_count": 2, "items": [{"etag": "53681d722c722d1d61d96b710c26866d89a36958", "charge_code": "084755310002", "classification": {"type": "charge-description", "description": "A registered charge"}, "charge_number": 2, "status": "outstanding", "delivered_on": "2022-09-22", "created_on": "2022-09-15", "particulars": {"contains_floating_charge": true, "contains_fixed_charge": true, "floating_charge_covers_all": true, "contains_negative_pledge": true}, "persons_entitled": [{"name": "Barclays Security Trustee Limited"}], "transactions": [{"filing_type": "create-charge-with-deed", "delivered_on": "2022-09-22", "links": {"filing": "/company/08475531/filing-history/MzM1MjU5NDQzM2FkaXF6a2N4"}}], "links": {"self": "/company/08475531/charges/ffYnTdxQYEIbbCmvm2rnFolQ-2E"}}, {"etag": "a4546e951a153c660f4929ae5fb64591c8a4e214", "charge_code": "084755310001", "classification": {"type": "charge-description", "description": "A registered charge"}, "charge_number": 1, "status": "fully-satisfied", "delivered_on": "2020-10-08", "created_on": "2020-09-29", "satisfied_on": "2026-03-16", "particulars": {"contains_floating_charge": true, "contains_fixed_charge": true, "floating_charge_covers_all": true, "contains_negative_pledge": true}, "persons_entitled": [{"name": "Barclays Security Trustee Limited"}], "transactions": [{"filing_type": "create-charge-with-deed", "delivered_on": "2020-10-08", "links": {"filing": "/company/08475531/filing-history/MzI4MDA0MjE4N2FkaXF6a2N4"}}, {"filing_type": "charge-satisfaction", "delivered_on": "2026-03-16", "links": {"filing": "/company/08475531/filing-history/MzUxMDU1NTg4MWFkaXF6a2N4"}}], "links": {"self": "/company/08475531/charges/EKae5aAsHvgescShDAVRbNPC0jE"}}]}