{"total_count": 1, "items": [{"etag": "5b4ab5517bcbb8ce0ac2d2200d31d0d29574edf6", "charge_code": "103000520001", "classification": {"type": "charge-description", "description": "A registered charge"}, "charge_number": 1, "status": "outstanding", "delivered_on": "2025-07-22", "created_on": "2025-07-18", "particulars": {"contains_floating_charge": true, "contains_fixed_charge": true, "floating_charge_covers_all": true, "contains_negative_pledge": true}, "persons_entitled": [{"name": "Rbs Invoice Finance Limited"}], "transactions": [{"filing_type": "create-charge-with-deed", "delivered_on": "2025-07-22", "links": {"filing": "/company/10300052/filing-history/MzQ3NDY3MDkwNGFkaXF6a2N4"}}], "links": {"self": "/company/10300052/charges/GdC0In7LjRNzTQSO-Yj2HEl83Y0"}}]}