{"total_count": 2, "items": [{"etag": "8bef31287080d639011b9170cdd01bb3e9d3ee31", "charge_code": "110712170002", "classification": {"type": "charge-description", "description": "A registered charge"}, "charge_number": 2, "status": "outstanding", "delivered_on": "2018-03-21", "created_on": "2018-03-09", "particulars": {"type": "brief-description", "description": "All that freehold interest in the land and property known as 119 harris way, sunbury on thames TW16 7EL and registered at the land registry with title absolute under title number SY710070. All that freehold interest in the land and property known as land on the west side of 121 harris way, sunbury-on-thames and registered at the land registry with title absolute under title number SY712650.", "contains_floating_charge": true, "contains_fixed_charge": true, "contains_negative_pledge": true}, "persons_entitled": [{"name": "Interbay Funding Limited"}], "transactions": [{"filing_type": "create-charge-with-deed", "delivered_on": "2018-03-21", "links": {"filing": "/company/11071217/filing-history/MzIwMDYwOTk3NWFkaXF6a2N4"}}], "links": {"self": "/company/11071217/charges/_-mtlJoNue6ICoV358zlV0WGkWo"}}, {"etag": "e0fe26182c4ad77eb9c7da606eb63ceabf065ca5", "charge_code": "110712170001", "classification": {"type": "charge-description", "description": "A registered charge"}, "charge_number": 1, "status": "outstanding", "delivered_on": "2018-03-21", "created_on": "2018-03-09", "particulars": {"type": "brief-description", "description": "All that freehold interest in the land and property known as 119 harris way, sunbury on thames TW16 7EL and registered at the land registry with title absolute under title number SY710070. All that freehold interest in the land and property known as land on the west side of 121 harris way, sunbury-on-thames and registered at the land registry with title absolute under title number SY712650.", "contains_floating_charge": true, "contains_fixed_charge": true, "floating_charge_covers_all": true, "contains_negative_pledge": true}, "persons_entitled": [{"name": "Interbay Funding Limited"}], "transactions": [{"filing_type": "create-charge-with-deed", "delivered_on": "2018-03-21", "links": {"filing": "/company/11071217/filing-history/MzIwMDYxMDYzNmFkaXF6a2N4"}}], "links": {"self": "/company/11071217/charges/Z3GwVE5RQCQmuw9uPE942YP7qT8"}}]}