{"total_count": 1, "items": [{"etag": "bfd43b51ec6c3b7961d16646ef083e8f1abeec43", "charge_code": "120572350001", "classification": {"type": "charge-description", "description": "A registered charge"}, "charge_number": 1, "status": "outstanding", "delivered_on": "2020-03-04", "created_on": "2020-02-28", "particulars": {"type": "brief-description", "description": "27 plimsoll close, london, E14 6EJ.", "contains_fixed_charge": true, "contains_negative_pledge": true}, "persons_entitled": [{"name": "Kensington Mortgage Company Limited"}], "transactions": [{"filing_type": "create-charge-with-deed", "delivered_on": "2020-03-04", "links": {"filing": "/company/12057235/filing-history/MzI1ODkyNTA3NWFkaXF6a2N4"}}], "links": {"self": "/company/12057235/charges/IwpO1G8r_qyaa-SD5inCeq-P1p8"}}]}