{"total_count": 3, "items": [{"etag": "ddf3b674d57d316587699b4b94f54ad80e4c7c94", "charge_code": "129313010003", "classification": {"type": "charge-description", "description": "A registered charge"}, "charge_number": 3, "status": "outstanding", "delivered_on": "2024-12-23", "created_on": "2024-12-20", "particulars": {"contains_floating_charge": true, "contains_fixed_charge": true, "floating_charge_covers_all": true, "contains_negative_pledge": true}, "persons_entitled": [{"name": "Oaknorth Bank PLC"}], "transactions": [{"filing_type": "create-charge-with-deed", "delivered_on": "2024-12-23", "links": {"filing": "/company/12931301/filing-history/MzQ0ODc0Mjc1MWFkaXF6a2N4"}}], "links": {"self": "/company/12931301/charges/qJK5-hpGvDPg9MY_uDTixJXbbqw"}}, {"etag": "3a8757fbfa3c8d34f3481ae29c3c7b69471669b7", "charge_code": "129313010002", "classification": {"type": "charge-description", "description": "A registered charge"}, "charge_number": 2, "status": "fully-satisfied", "delivered_on": "2023-10-13", "created_on": "2023-10-11", "satisfied_on": "2025-01-07", "particulars": {"type": "brief-description", "description": "N/A.", "contains_floating_charge": true, "contains_fixed_charge": true, "floating_charge_covers_all": true, "contains_negative_pledge": true}, "persons_entitled": [{"name": "Cbre Loan Services Limited as Security Trustee for and on Behalf of the Common Secured Parties (As Defined in the Instrument)"}], "transactions": [{"filing_type": "create-charge-with-deed", "delivered_on": "2023-10-13", "links": {"filing": "/company/12931301/filing-history/MzM5NjUwMzY3NGFkaXF6a2N4"}}, {"filing_type": "charge-satisfaction", "delivered_on": "2025-01-07", "links": {"filing": "/company/12931301/filing-history/MzQ1MDE5NjYzOWFkaXF6a2N4"}}], "links": {"self": "/company/12931301/charges/xcqQuHYPfZqOti2NUj6_rfb7IA0"}}, {"etag": "1064f942b79628e1f5d1021cf03c8f60390328a5", "charge_code": "129313010001", "classification": {"type": "charge-description", "description": "A registered charge"}, "charge_number": 1, "status": "fully-satisfied", "delivered_on": "2020-11-11", "created_on": "2020-11-06", "satisfied_on": "2025-01-07", "particulars": {"contains_floating_charge": true, "contains_fixed_charge": true, "floating_charge_covers_all": true, "contains_negative_pledge": true}, "persons_entitled": [{"name": "Cbre Loan Services Limited as Security Trustee for and on Behalf of the Common Secured Parties (As Defined in the Instrument)."}], "transactions": [{"filing_type": "create-charge-with-deed", "delivered_on": "2020-11-11", "links": {"filing": "/company/12931301/filing-history/MzI4MzE3MTA1MWFkaXF6a2N4"}}, {"filing_type": "charge-satisfaction", "delivered_on": "2025-01-07", "links": {"filing": "/company/12931301/filing-history/MzQ1MDE5NjUwNGFkaXF6a2N4"}}], "links": {"self": "/company/12931301/charges/hdM42RTPozy3bXwrCfrWBvs1BNM"}}]}