{"total_count": 3, "items": [{"etag": "c558455875626dac08e01bb5bfd6da405ab7d321", "charge_code": "132731790003", "classification": {"type": "charge-description", "description": "A registered charge"}, "charge_number": 3, "status": "outstanding", "delivered_on": "2021-11-22", "created_on": "2021-11-18", "particulars": {"type": "brief-description", "description": "Leasehold properties - flat 1, 16-18 theobald street borehamwood WD6 4SE - not yet registered at the land registry / flat 2, 16-18 theobald street. Borehamwood WD6 4SE - not yet registered at the land registry / flat 3, 16-18 theobald street borehamwood WD6 4SE - not yet registered at the. Land registry / flat 4, 16-18 theobald street borehamwood WD6 4SE - not yet registered at the land registry / flat 5, 16-18 theobald street. Borehamwood WD6 4SE - not yet registered at the land registry / flat 6,16-18 theobald street borehamwood WD6 4SE - not yet registered at the. Land registry.", "contains_fixed_charge": true, "contains_negative_pledge": true}, "persons_entitled": [{"name": "United National Bank Limited"}], "transactions": [{"filing_type": "create-charge-with-deed", "delivered_on": "2021-11-22", "links": {"filing": "/company/13273179/filing-history/MzMyMDg2MjQzOWFkaXF6a2N4"}}], "links": {"self": "/company/13273179/charges/18aL3FCjvmx2jBNYJEKNHJpN-vo"}}, {"etag": "9dc5f182a0bfb91d4611afbe5757c1b0623799f6", "charge_code": "132731790001", "classification": {"type": "charge-description", "description": "A registered charge"}, "charge_number": 1, "status": "outstanding", "delivered_on": "2021-11-19", "created_on": "2021-11-18", "particulars": {"type": "brief-description", "description": "Leasehold properties - flat 1, 16-18 theobald street borehamwood WD6 4SE - not yet registered at the land registry / flat 2, 16-18 theobald street borehamwood WD6 4SE - not yet registered at the land registry / flat 3, 16-18 theobald street borehamwood WD6 4SE - not yet registered at the land registry / flat 4, 16-18 theobald street borehamwood WD6 4SE - not yet registered at the land registry / flat 5, 16-18 theobald street borehamwood WD6 4SE - not yet registered at the land registry / flat 6,16-18 theobald street borehamwood WD6 4SE - not yet registered at the land registry.", "contains_floating_charge": true, "contains_fixed_charge": true, "floating_charge_covers_all": true, "contains_negative_pledge": true}, "persons_entitled": [{"name": "United National Bank Limited"}], "transactions": [{"filing_type": "create-charge-with-deed", "delivered_on": "2021-11-19", "links": {"filing": "/company/13273179/filing-history/MzMyMDY5MDQ2OGFkaXF6a2N4"}}], "links": {"self": "/company/13273179/charges/OAe1h642J30i0mWTNR4JzCFqrL0"}}, {"etag": "2e71dc4bab96f0d4f4dc7c1b87395bd635154996", "charge_code": "132731790002", "classification": {"type": "charge-description", "description": "A registered charge"}, "charge_number": 2, "status": "outstanding", "delivered_on": "2021-11-22", "created_on": "2021-11-17", "particulars": {"type": "brief-description", "description": "All monies standing to the credit of the deposit account held with united national bank limited.", "contains_negative_pledge": true}, "persons_entitled": [{"name": "United National Bank Limited"}], "transactions": [{"filing_type": "create-charge-with-deed", "delivered_on": "2021-11-22", "links": {"filing": "/company/13273179/filing-history/MzMyMDg2MTI3M2FkaXF6a2N4"}}], "links": {"self": "/company/13273179/charges/5gw6oUpleUXFof7WoEH5eMg98L8"}}]}