{"total_count": 3, "items": [{"etag": "1ad3078b8c4cf2131e446cfd42cc8fe1db73d765", "charge_code": "139632150003", "classification": {"type": "charge-description", "description": "A registered charge"}, "charge_number": 3, "status": "outstanding", "delivered_on": "2025-09-11", "created_on": "2025-09-05", "particulars": {"type": "brief-description", "description": "5 manscroft road, hemel hempstead, hertfordshire HP1 3HU.", "contains_negative_pledge": true}, "persons_entitled": [{"name": "The Mortgage Works (UK) PLC"}], "transactions": [{"filing_type": "create-charge-with-deed", "delivered_on": "2025-09-11", "links": {"filing": "/company/13963215/filing-history/MzQ4MDU0MzczNWFkaXF6a2N4"}}], "links": {"self": "/company/13963215/charges/FRxB7a06h6BfpmgVEvyW0TWc8h0"}}, {"etag": "65be7fa073c1baf093cdd03637168acad91186f5", "charge_code": "139632150002", "classification": {"type": "charge-description", "description": "A registered charge"}, "charge_number": 2, "status": "outstanding", "delivered_on": "2025-01-20", "created_on": "2025-01-17", "particulars": {"type": "brief-description", "description": "Legal mortgage over property situated at 46 paxford road, wembley HA0 3RQ (title number P49391).", "contains_fixed_charge": true, "contains_negative_pledge": true}, "persons_entitled": [{"name": "Quantum Mortgages Limited (Company Number: 13628831)"}], "transactions": [{"filing_type": "create-charge-with-deed", "delivered_on": "2025-01-20", "links": {"filing": "/company/13963215/filing-history/MzQ1MTg5NDI1MWFkaXF6a2N4"}}], "links": {"self": "/company/13963215/charges/h2JV7lzvu6iBz2V36NMb2yMWHkA"}}, {"etag": "6279053b93ea09457c7cfdd045150d25b3fd0e56", "charge_code": "139632150001", "classification": {"type": "charge-description", "description": "A registered charge"}, "charge_number": 1, "status": "outstanding", "delivered_on": "2022-08-17", "created_on": "2022-08-12", "particulars": {"type": "brief-description", "description": "7 aspfield row, hemel hempstead, HP1 3HE (and registered under title number HD239993).", "contains_fixed_charge": true, "contains_negative_pledge": true}, "persons_entitled": [{"name": "Landbay Partners Limited"}], "transactions": [{"filing_type": "create-charge-with-deed", "delivered_on": "2022-08-17", "links": {"filing": "/company/13963215/filing-history/MzM0ODk0NzYzNGFkaXF6a2N4"}}], "links": {"self": "/company/13963215/charges/vCE5CK5z6XaZT0njxGEdzR2ClmI"}}]}