{"total_count": 1, "items": [{"etag": "44ed2c9bc3823f31f1ba5839b889b21ffe28b598", "charge_code": "142491890001", "classification": {"type": "charge-description", "description": "A registered charge"}, "charge_number": 1, "status": "outstanding", "delivered_on": "2026-06-25", "created_on": "2026-06-19", "particulars": {"contains_floating_charge": true, "contains_fixed_charge": true, "floating_charge_covers_all": true, "contains_negative_pledge": true}, "persons_entitled": [{"name": "Nucleus Cash Flow FINANCE2 Limited"}], "transactions": [{"filing_type": "create-charge-with-deed", "delivered_on": "2026-06-25", "links": {"filing": "/company/14249189/filing-history/MzUyODUzNjIyNmFkaXF6a2N4"}}], "links": {"self": "/company/14249189/charges/CUgJOqx82cdmyQB6PXswGK9vMdY"}}]}