{"total_count": 1, "items": [{"etag": "e6e0556ebd0de5310f68de48e0ff397b700e7b85", "charge_code": "148976480001", "classification": {"type": "charge-description", "description": "A registered charge"}, "charge_number": 1, "status": "outstanding", "delivered_on": "2025-10-03", "created_on": "2025-10-01", "particulars": {"type": "brief-description", "description": "The leasehold property known as the second and third floor basements and other land being the second and third floor basements and other land being part of 39 to 42 grosvenor square and 39 to 42 adams's row as is more particularly described in a lease dated 7 october 1974 made between (1) jermyn investment co. Limited and (2) national car parks limited.. Title number: NGL254193.", "contains_floating_charge": true, "contains_fixed_charge": true, "floating_charge_covers_all": true, "contains_negative_pledge": true}, "persons_entitled": [{"name": "Mera Im Agent Limited"}], "transactions": [{"filing_type": "create-charge-with-deed", "delivered_on": "2025-10-03", "links": {"filing": "/company/14897648/filing-history/MzQ4MzczMTIwNmFkaXF6a2N4"}}], "links": {"self": "/company/14897648/charges/hvrk_-ksDaqnDDZd3a0rg8jXvg0"}}]}