{"total_count": 3, "items": [{"etag": "4795fc8cd8c1cdd8ff3b8808b926bd775d120d8b", "charge_code": "153189770003", "classification": {"type": "charge-description", "description": "A registered charge"}, "charge_number": 3, "status": "outstanding", "delivered_on": "2025-07-25", "created_on": "2025-07-21", "particulars": {"type": "brief-description", "description": "Freehold land known as 15 ripon street, grimsby, DN31 2HG, registered at hm land registry under title number HS55835.", "contains_negative_pledge": true}, "persons_entitled": [{"name": "Aldermore Bank PLC"}], "transactions": [{"filing_type": "create-charge-with-deed", "delivered_on": "2025-07-25", "links": {"filing": "/company/15318977/filing-history/MzQ3NTE0MzkxM2FkaXF6a2N4"}}], "links": {"self": "/company/15318977/charges/iNLw02T7RnFHb713rk20ej08Mfg"}}, {"etag": "f82d93fbf71262698c57e2e0d13b4eb2b844d128", "charge_code": "153189770002", "classification": {"type": "charge-description", "description": "A registered charge"}, "charge_number": 2, "status": "outstanding", "delivered_on": "2024-07-19", "created_on": "2024-07-12", "particulars": {"type": "brief-description", "description": "Freehold property at 15 ripon street grimsby DN31 2HG.", "contains_floating_charge": true, "contains_fixed_charge": true, "floating_charge_covers_all": true, "contains_negative_pledge": true}, "persons_entitled": [{"name": "Together Commercial Finance Limited"}], "transactions": [{"filing_type": "create-charge-with-deed", "delivered_on": "2024-07-19", "links": {"filing": "/company/15318977/filing-history/MzQyOTQ0MTU4MGFkaXF6a2N4"}}], "links": {"self": "/company/15318977/charges/qzsTTMZqGUQxJh86_dWkZdnxpGQ"}}, {"etag": "81696ece77ca340ba3088e379180b4c8964bcb0e", "charge_code": "153189770001", "classification": {"type": "charge-description", "description": "A registered charge"}, "charge_number": 1, "status": "outstanding", "delivered_on": "2024-07-19", "created_on": "2024-07-12", "particulars": {"type": "brief-description", "description": "Freehold property at 15 ripon street grimsby DN31 2HG.", "contains_fixed_charge": true}, "persons_entitled": [{"name": "Together Commercial Finance Limited"}], "transactions": [{"filing_type": "create-charge-with-deed", "delivered_on": "2024-07-19", "links": {"filing": "/company/15318977/filing-history/MzQyOTQ0MjczOWFkaXF6a2N4"}}], "links": {"self": "/company/15318977/charges/P7N6gZCi3KEetHSawH9NMcbZL80"}}]}