{"total_count": 1, "items": [{"etag": "e44c9267f4f679a39e6cf705cea0749282d32920", "charge_code": "155537950001", "classification": {"type": "charge-description", "description": "A registered charge"}, "charge_number": 1, "status": "outstanding", "delivered_on": "2024-10-31", "created_on": "2024-10-25", "particulars": {"contains_floating_charge": true, "contains_fixed_charge": true, "floating_charge_covers_all": true, "contains_negative_pledge": true}, "persons_entitled": [{"name": "Jake Beardsley"}], "transactions": [{"filing_type": "create-charge-with-deed", "delivered_on": "2024-10-31", "links": {"filing": "/company/15553795/filing-history/MzQ0MTU4NDY4N2FkaXF6a2N4"}}], "links": {"self": "/company/15553795/charges/OlVZkE_nFteNl3ZWw0NslRMRvlU"}}]}