{"total_count": 2, "items": [{"etag": "5f02bd587961725f34a599ecf13f4c1d21bfc04c", "classification": {"type": "charge-description", "description": "Standard security"}, "charge_number": 3, "status": "fully-satisfied", "delivered_on": "1993-05-12", "created_on": "1993-04-23", "satisfied_on": "2019-11-27", "particulars": {"type": "short-particulars", "description": "Part of densfield works, north isla street, dundee as relative to disposition by tck group limited in favour of the company."}, "secured_details": {"type": "amount-secured", "description": "All sums due or to become due"}, "persons_entitled": [{"name": "The Royal Bank of Scotland PLC"}], "transactions": [{"filing_type": "create-charge-scotland-pre-2006-companies-act", "delivered_on": "1993-05-12", "links": {"filing": "/company/SC062835/filing-history/MDE1Mzk2OTUxN2FkaXF6a2N4"}}, {"filing_type": "charge-satisfaction", "delivered_on": "2019-11-27", "links": {"filing": "/company/SC062835/filing-history/MzI1MDQ4ODcxNWFkaXF6a2N4"}}], "links": {"self": "/company/SC062835/charges/KQ8NBhM20wHEI-WyjSFA2YbykkI"}}, {"etag": "f442ff83d24bf5dce99e8cbd3c84d87ef06d236e", "classification": {"type": "charge-description", "description": "Bond & floating charge"}, "charge_number": 1, "status": "fully-satisfied", "delivered_on": "1984-03-20", "created_on": "1984-03-12", "satisfied_on": "2022-01-20", "particulars": {"type": "short-particulars", "description": "Undertaking and all property and assets present and future of the company including uncalled capital.", "contains_floating_charge": true}, "secured_details": {"type": "amount-secured", "description": "All sums due or to become due"}, "scottish_alterations": {"has_restricting_provisions": true}, "persons_entitled": [{"name": "The Royal Bank of Scotland PLC"}], "transactions": [{"filing_type": "create-charge", "delivered_on": "1984-03-20"}, {"filing_type": "charge-satisfaction", "delivered_on": "2022-01-20", "links": {"filing": "/company/SC062835/filing-history/MzMyNzI3MzkxOWFkaXF6a2N4"}}], "links": {"self": "/company/SC062835/charges/CdqXnHCz9idsADqcL9y1GZ11otU"}}]}