{"total_count": 3, "items": [{"etag": "b6d872753784d97ddd52514e805abeaeb4d9bfee", "charge_code": "SC2930160003", "classification": {"type": "charge-description", "description": "A registered charge"}, "charge_number": 3, "status": "outstanding", "delivered_on": "2013-07-04", "created_on": "2013-06-28", "particulars": {"type": "brief-description", "description": "Notification of addition to or amendment of charge.", "contains_floating_charge": true, "floating_charge_covers_all": true}, "persons_entitled": [{"name": "Clydesdale Bank PLC"}], "transactions": [{"filing_type": "create-charge-with-deed", "delivered_on": "2013-07-04", "links": {"filing": "/company/SC293016/filing-history/MzA4MTE1NzA0NmFkaXF6a2N4"}}], "links": {"self": "/company/SC293016/charges/nq-nz1AQIY7TgLZEnFf90qkv9eI"}}, {"etag": "646c9701c58dbf90fe88fede05a2ce9e27e040bf", "classification": {"type": "charge-description", "description": "Floating charge"}, "charge_number": 2, "status": "outstanding", "delivered_on": "2009-12-05", "created_on": "2009-12-02", "particulars": {"type": "short-particulars", "description": "Undertaking & all property & assets present & future, including uncalled capital.", "contains_floating_charge": true}, "secured_details": {"type": "amount-secured", "description": "All sums due or to become due"}, "scottish_alterations": {"has_restricting_provisions": true}, "persons_entitled": [{"name": "Clydesdale Bank PLC"}], "transactions": [{"filing_type": "create-charge-scotland-pre-april-2013", "delivered_on": "2009-12-05", "links": {"filing": "/company/SC293016/filing-history/MzAwNDUwNzQ0N2FkaXF6a2N4"}}], "links": {"self": "/company/SC293016/charges/VL-UmeDNEqF22LpG3zVhkji8bz8"}}, {"etag": "ad0cbb6704ba1b33fb7ad7c144e2c234d7688929", "classification": {"type": "charge-description", "description": "Floating charge"}, "charge_number": 1, "status": "fully-satisfied", "delivered_on": "2006-10-28", "created_on": "2006-10-25", "satisfied_on": "2010-02-02", "particulars": {"type": "short-particulars", "description": "Undertaking and all property and assets present and future of the company including uncalled capital.", "contains_floating_charge": true}, "secured_details": {"type": "amount-secured", "description": "All sums due or to become due"}, "scottish_alterations": {"has_restricting_provisions": true}, "persons_entitled": [{"name": "Hsbc Bank PLC"}], "transactions": [{"filing_type": "create-charge-scotland-pre-2006-companies-act", "delivered_on": "2006-10-28", "links": {"filing": "/company/SC293016/filing-history/MDE3MDI4MjMzN2FkaXF6a2N4"}}, {"filing_type": "charge-satisfaction-floating-charge-in-scotland-pre-april-2013", "delivered_on": "2010-02-02", "links": {"filing": "/company/SC293016/filing-history/MzAwODQ4ODMxOWFkaXF6a2N4"}}], "links": {"self": "/company/SC293016/charges/LGZfcpkvBpVet-6E8kO-Q9ovM9A"}}]}