{"total_count": 1, "items": [{"etag": "30817223c9a6f584839026594bb83731fc8808a6", "charge_code": "SC5450250001", "classification": {"type": "charge-description", "description": "A registered charge"}, "charge_number": 1, "status": "outstanding", "delivered_on": "2022-11-28", "created_on": "2022-11-14", "particulars": {"type": "brief-description", "description": "The whole of the assets, property and undertaking of the borrower for the time being and from time to time including all uncalled share capital.", "contains_floating_charge": true, "floating_charge_covers_all": true, "contains_negative_pledge": true}, "persons_entitled": [{"name": "Dsl Business Finance Limited (SC145739)"}], "transactions": [{"filing_type": "create-charge-with-deed", "delivered_on": "2022-11-28", "links": {"filing": "/company/SC545025/filing-history/MzM1OTk4NzAzNWFkaXF6a2N4"}}], "links": {"self": "/company/SC545025/charges/_PGYWBs-z26yNRgRlLN7ta_YAW4"}}]}