{"total_count": 1, "items": [{"etag": "5eebf6c3a797ca914b98923b01b39836ef4ed574", "charge_code": "SC6991940001", "classification": {"type": "charge-description", "description": "A registered charge"}, "charge_number": 1, "status": "outstanding", "delivered_on": "2023-12-28", "created_on": "2023-12-21", "particulars": {"contains_floating_charge": true, "floating_charge_covers_all": true, "contains_negative_pledge": true}, "persons_entitled": [{"name": "The Royal Bank of Scotland PLC"}], "transactions": [{"filing_type": "create-charge-with-deed", "delivered_on": "2023-12-28", "links": {"filing": "/company/SC699194/filing-history/MzQwNTgwNDczNGFkaXF6a2N4"}}], "links": {"self": "/company/SC699194/charges/kRIXGRqkh5j8P_D-uO2TDB3axUg"}}]}